mopidy_podcast_itunes/__init__.py
mopidy_podcast_itunes/backend.py
mopidy_podcast_itunes/client.py
mopidy_podcast_itunes/ext.conf
mopidy_podcast_itunes/library.py
mopidy_podcast_itunes/translator.py
Mopidy_Podcast_iTunes-3.0.1.dist-info/LICENSE
Mopidy_Podcast_iTunes-3.0.1.dist-info/METADATA
Mopidy_Podcast_iTunes-3.0.1.dist-info/WHEEL
Mopidy_Podcast_iTunes-3.0.1.dist-info/entry_points.txt
Mopidy_Podcast_iTunes-3.0.1.dist-info/top_level.txt
Mopidy_Podcast_iTunes-3.0.1.dist-info/RECORD
